[
    {
        "id": 1,
        "slide": 1,
        "fecha": "2025-11-02 22:24:55"
    },
    {
        "id": 2,
        "slide": 0,
        "fecha": "2025-11-02 22:25:02"
    },
    {
        "id": 3,
        "slide": 3,
        "fecha": "2025-11-02 22:24:48"
    },
    {
        "id": 4,
        "slide": 0,
        "fecha": "2025-11-02 22:25:00"
    },
    {
        "id": 5,
        "slide": 22,
        "fecha": "2025-11-02 22:41:36"
    },
    {
        "id": 6,
        "slide": 22,
        "fecha": "2025-11-02 23:11:53"
    },
    {
        "id": 7,
        "slide": 23,
        "fecha": "2025-11-02 23:17:45"
    },
    {
        "id": 8,
        "slide": 26,
        "fecha": "2025-11-02 23:19:00"
    }
]